abs_exception_core/__init__.py
abs_exception_core/exception_handlers.py
abs_exception_core/exceptions.py
abs_exception_core-0.2.3.dist-info/METADATA
abs_exception_core-0.2.3.dist-info/WHEEL
abs_exception_core-0.2.3.dist-info/RECORD
