Metadata-Version: 2.3
Name: abs-exception-core
Version: 0.2.3
Summary: Shared base exception utilities for FastAPI apps.
License: MIT
Author: AutoBridgeSystems
Author-email: info@autobridgesystems.com
Requires-Python: >=3.11,<4.0
Classifier: License :: OSI Approved :: MIT License
Classifier: Programming Language :: Python :: 3
Classifier: Programming Language :: Python :: 3.11
Classifier: Programming Language :: Python :: 3.12
Classifier: Programming Language :: Python :: 3.13
Requires-Dist: fastapi[standard] (>=0.115.2)
